geoserver_acceptance_tests/.gitignore
geoserver_acceptance_tests/README.md
geoserver_acceptance_tests/__init__.py
geoserver_acceptance_tests/cli.py
geoserver_acceptance_tests/compose/example.compose.yaml
geoserver_acceptance_tests/compose/geodatabase/001_create_schemas.sql
geoserver_acceptance_tests/config.py
geoserver_acceptance_tests/data/sampledata.tgz
geoserver_acceptance_tests/example.config.yaml
geoserver_acceptance_tests/tests/__init__.py
geoserver_acceptance_tests/tests/conftest.py
geoserver_acceptance_tests/tests/resources/__init__.py
geoserver_acceptance_tests/tests/resources/i18n/__init__.py
geoserver_acceptance_tests/tests/resources/i18n/labels/default_locale/default_value/language_None_expected.png
geoserver_acceptance_tests/tests/resources/i18n/labels/default_locale/default_value/language__expected.png
geoserver_acceptance_tests/tests/resources/i18n/labels/default_locale/default_value/language_de_expected.png
geoserver_acceptance_tests/tests/resources/i18n/labels/default_locale/default_value/language_fr_expected.png
geoserver_acceptance_tests/tests/resources/i18n/labels/default_locale/default_value/language_it_expected.png
geoserver_acceptance_tests/tests/resources/i18n/labels/default_locale/no_default_value/language_None_expected.png
geoserver_acceptance_tests/tests/resources/i18n/labels/default_locale/no_default_value/language__expected.png
geoserver_acceptance_tests/tests/resources/i18n/labels/default_locale/no_default_value/language_it_expected.png
geoserver_acceptance_tests/tests/resources/i18n/labels/no_default_locale/default_value/language_None_expected.png
geoserver_acceptance_tests/tests/resources/i18n/labels/no_default_locale/default_value/language__expected.png
geoserver_acceptance_tests/tests/resources/i18n/labels/no_default_locale/default_value/language_de_expected.png
geoserver_acceptance_tests/tests/resources/i18n/labels/no_default_locale/default_value/language_fr_expected.png
geoservercloud-0.8.2.dist-info/LICENSE
geoservercloud-0.8.2.dist-info/METADATA
geoservercloud-0.8.2.dist-info/WHEEL
geoservercloud-0.8.2.dist-info/entry_points.txt
geoservercloud-0.8.2.dist-info/RECORD
