Metadata-Version: 2.3
Name: geoservercloud
Version: 0.8.2
Summary: Lightweight Python client to interact with GeoServer Cloud REST API, GeoServer ACL and OGC services
License: BSD-2-Clause
Author: Camptocamp
Author-email: info@camptocamp.com
Requires-Python: >=3.10
Classifier: License :: OSI Approved :: BSD License
Classifier: Programming Language :: Python :: 3
Classifier: Programming Language :: Python :: 3.10
Classifier: Programming Language :: Python :: 3.11
Classifier: Programming Language :: Python :: 3.12
Classifier: Programming Language :: Python :: 3.13
Requires-Dist: OWSLib
Requires-Dist: psycopg2-binary
Requires-Dist: pytest
Requires-Dist: requests
Requires-Dist: sqlalchemy
Requires-Dist: xmltodict
